openchatbi/__init__.py
openchatbi/agent_graph.py
openchatbi/config.yaml.template
openchatbi/config_loader.py
openchatbi/constants.py
openchatbi/context_config.py
openchatbi/context_manager.py
openchatbi/graph_state.py
openchatbi/text_segmenter.py
openchatbi/utils.py
openchatbi/catalog/__init__.py
openchatbi/catalog/catalog_loader.py
openchatbi/catalog/catalog_store.py
openchatbi/catalog/factory.py
openchatbi/catalog/helper.py
openchatbi/catalog/retrival_helper.py
openchatbi/catalog/schema_retrival.py
openchatbi/catalog/token_service.py
openchatbi/catalog/store/__init__.py
openchatbi/catalog/store/file_system.py
openchatbi/code/docker_executor.py
openchatbi/code/executor_base.py
openchatbi/code/local_executor.py
openchatbi/code/restricted_local_executor.py
openchatbi/llm/llm.py
openchatbi/prompts/agent_prompt.md
openchatbi/prompts/extraction_prompt.md
openchatbi/prompts/schema_linking_prompt.md
openchatbi/prompts/system_prompt.py
openchatbi/prompts/text2sql_prompt.md
openchatbi/prompts/visualization_prompt.md
openchatbi/prompts/sql_dialect/presto.md
openchatbi/text2sql/__init__.py
openchatbi/text2sql/data.py
openchatbi/text2sql/extraction.py
openchatbi/text2sql/generate_sql.py
openchatbi/text2sql/schema_linking.py
openchatbi/text2sql/sql_graph.py
openchatbi/text2sql/text2sql_utils.py
openchatbi/text2sql/visualization.py
openchatbi/tool/ask_human.py
openchatbi/tool/mcp_tools.py
openchatbi/tool/memory.py
openchatbi/tool/run_python_code.py
openchatbi/tool/save_report.py
openchatbi/tool/search_knowledge.py
openchatbi-0.1.1.dist-info/METADATA
openchatbi-0.1.1.dist-info/WHEEL
openchatbi-0.1.1.dist-info/licenses/LICENSE
openchatbi-0.1.1.dist-info/RECORD
