Metadata-Version: 2.4
Name: openchatbi
Version: 0.1.1
Summary: OpenChatBI - Natural language business intelligence powered by LLMs for intuitive data analysis and SQL generation
Project-URL: Homepage, https://github.com/zhongyu09/openchatbi
Project-URL: Repository, https://github.com/zhongyu09/openchatbi
Project-URL: Documentation, https://github.com/zhongyu09/openchatbi/tree/main
Project-URL: Bug Tracker, https://github.com/zhongyu09/openchatbi/issues
Author-email: Yu Zhong <zhongyu8@gmail.com>
License: MIT
License-File: LICENSE
Keywords: agent,ai,analytics,analyze data,bi,business intelligence,conversational ai,data agent,database,gpt,langchain,langgraph,llm,machine learning,natural language,nlp,query data,talk to data,text2sql
Classifier: Development Status :: 3 - Alpha
Classifier: Intended Audience :: Developers
Classifier: Intended Audience :: End Users/Desktop
Classifier: Intended Audience :: Science/Research
Classifier: License :: OSI Approved :: MIT License
Classifier: Operating System :: OS Independent
Classifier: Programming Language :: Python :: 3
Classifier: Programming Language :: Python :: 3.11
Classifier: Topic :: Database
Classifier: Topic :: Office/Business
Classifier: Topic :: Scientific/Engineering :: Artificial Intelligence
Classifier: Topic :: Scientific/Engineering :: Information Analysis
Classifier: Topic :: Software Development :: Libraries :: Python Modules
Requires-Python: <4.0,>=3.11
Requires-Dist: aiosqlite>=0.21.0
Requires-Dist: docker<8.0.0,>=7.0.0
Requires-Dist: gradio<6.0.0,>=5.43.1
Requires-Dist: json5<1.0.0,>=0.10.0
Requires-Dist: langchain-anthropic<1.0.0,>=0.3.13
Requires-Dist: langchain-chroma>=0.2.5
Requires-Dist: langchain-community<1.0.0,>=0.3.27
Requires-Dist: langchain-mcp-adapters>=0.1.9
Requires-Dist: langchain-openai<1.0.0,>=0.3.18
Requires-Dist: langgraph-checkpoint-sqlite>=2.0.11
Requires-Dist: langgraph<1.0.0,>=0.4.7
Requires-Dist: langmem>=0.0.29
Requires-Dist: matplotlib<4.0.0,>=3.10.6
Requires-Dist: numpy<3.0.0,>=2.3.0
Requires-Dist: pandas<3.0.0,>=2.2.0
Requires-Dist: plotly<6.0.0,>=5.17.0
Requires-Dist: pyhive[presto]>=0.7.0
Requires-Dist: pysqlite3>=0.5.4
Requires-Dist: python-levenshtein>=0.27.1
Requires-Dist: rank-bm25<1.0.0,>=0.2.2
Requires-Dist: requests<3.0.0,>=2.31.0
Requires-Dist: restrictedpython<9.0,>=8.0
Requires-Dist: seaborn<1.0.0,>=0.13.0
Requires-Dist: sqlalchemy-trino>=0.5.0
Requires-Dist: sqlalchemy<3.0.0,>=2.0.41
Requires-Dist: streamlit<2.0.0,>=1.49.1
Provides-Extra: dev
Requires-Dist: aioresponses<1.0.0,>=0.7.7; extra == 'dev'
Requires-Dist: autodoc-pydantic; extra == 'dev'
Requires-Dist: bandit<2.0.0,>=1.8.6; extra == 'dev'
Requires-Dist: black<25.0.0,>=24.10.0; extra == 'dev'
Requires-Dist: langsmith[pytest]<1.0.0,>=0.4.8; extra == 'dev'
Requires-Dist: mypy<2.0.0,>=1.13.0; extra == 'dev'
Requires-Dist: myst-parser; extra == 'dev'
Requires-Dist: openevals<1.0.0,>=0.1.0; extra == 'dev'
Requires-Dist: pre-commit<5.0.0,>=4.0.1; extra == 'dev'
Requires-Dist: pytest-asyncio<1.0.0,>=0.23.8; extra == 'dev'
Requires-Dist: pytest-cov<7.0.0,>=6.0.0; extra == 'dev'
Requires-Dist: pytest-mock<4.0.0,>=3.14.0; extra == 'dev'
Requires-Dist: pytest-sugar<2.0.0,>=1.0.0; extra == 'dev'
Requires-Dist: pytest<9.0.0,>=7.4.0; extra == 'dev'
Requires-Dist: responses<1.0.0,>=0.25.3; extra == 'dev'
Requires-Dist: ruff<1.0.0,>=0.8.0; extra == 'dev'
Requires-Dist: sphinx-autodoc-typehints<3.0.0,>=2.5.0; extra == 'dev'
Requires-Dist: sphinx-rtd-theme<4.0.0,>=3.0.0; extra == 'dev'
Requires-Dist: sphinx<9.0.0,>=8.2.3; extra == 'dev'
Requires-Dist: twine<7.0.0,>=6.0.0; extra == 'dev'
Requires-Dist: types-setuptools>=75.6.0.20241126; extra == 'dev'
Provides-Extra: docs
Requires-Dist: autodoc-pydantic; extra == 'docs'
Requires-Dist: myst-parser; extra == 'docs'
Requires-Dist: sphinx-autodoc-typehints<3.0.0,>=2.5.0; extra == 'docs'
Requires-Dist: sphinx-rtd-theme<4.0.0,>=3.0.0; extra == 'docs'
Requires-Dist: sphinx<9.0.0,>=8.2.3; extra == 'docs'
Provides-Extra: test
Requires-Dist: aioresponses<1.0.0,>=0.7.7; extra == 'test'
Requires-Dist: langsmith[pytest]<1.0.0,>=0.4.8; extra == 'test'
Requires-Dist: openevals<1.0.0,>=0.1.0; extra == 'test'
Requires-Dist: pytest-asyncio<1.0.0,>=0.23.8; extra == 'test'
Requires-Dist: pytest-cov<7.0.0,>=6.0.0; extra == 'test'
Requires-Dist: pytest-mock<4.0.0,>=3.14.0; extra == 'test'
Requires-Dist: pytest-sugar<2.0.0,>=1.0.0; extra == 'test'
Requires-Dist: pytest<9.0.0,>=7.4.0; extra == 'test'
Requires-Dist: responses<1.0.0,>=0.25.3; extra == 'test'
